labs/Lab1/paquin_lab/src/const.v
`define SEL_NON 2'b00
`define SEL_REG 2'b01
`define SEL_MEM 2'b10
`define SEL_IMM 2'b11

`define PCSEL_INC 3'b000
`define PCSEL_JMP 3'b001
`define PCSEL_JE  3'b010
`define PCSEL_JNE 3'b011
`define PCSEL_HLT 3'b100

`define INST_HALT 4'b0000
`define INST_INC  4'b0001
`define INST_JMP  4'b0010
`define INST_JNE  4'b0011
`define INST_JE   4'b0100
`define INST_ADD  4'b0101
`define INST_SUB  4'b0110
`define INST_XOR  4'b0111
`define INST_CMP  4'b1000
`define INST_LIMM 4'b1001
`define INST_MOV  4'b1010
`define INST_SW   4'b1011
`define INST_LW   4'b1100
`define INST_SPEC 4'b1101

`define OP_NOP   4'b0000
`define OP_ADD   4'b0001
`define OP_SUB   4'b0010
`define OP_INC   4'b0011
`define OP_XOR   4'b0100
`define OP_CMP   4'b0101
`define OP_SADD  4'b0110
`define OP_SSUB  4'b0111
`define OP_SMULT 4'b1000
`define OP_SDIV  4'b1001
`define OP_A     4'b1010
`define OP_B     4'b1011

`define CHAR_SPACE 0
`define CHAR_A 1
`define CHAR_B 2
`define CHAR_C 3
`define CHAR_D 4
`define CHAR_E 5
`define CHAR_F 6
`define CHAR_G 7
`define CHAR_H 8
`define CHAR_I 9
`define CHAR_J 10
`define CHAR_K 11
`define CHAR_L 12
`define CHAR_M 13
`define CHAR_N 14
`define CHAR_O 15
`define CHAR_P 16
`define CHAR_Q 17
`define CHAR_R 18
`define CHAR_S 19
`define CHAR_T 20
`define CHAR_U 21
`define CHAR_V 22
`define CHAR_W 23
`define CHAR_X 24
`define CHAR_Y 25
`define CHAR_Z 26
`define CHAR_0 27
`define CHAR_1 28
`define CHAR_2 29
`define CHAR_3 30
`define CHAR_4 31
`define CHAR_5 32
`define CHAR_6 33
`define CHAR_7 34
`define CHAR_8 35
`define CHAR_9 36

`define SEG7_0 7'b0000001
`define SEG7_1 7'b1001111
`define SEG7_2 7'b0010010
`define SEG7_3 7'b0000110
`define SEG7_4 7'b1001100
`define SEG7_5 7'b0100100
`define SEG7_6 7'b0100000
`define SEG7_7 7'b0001111
`define SEG7_8 7'b0000000
`define SEG7_9 7'b0000100

labs/Lab1/paquin_lab/src/compiler.v
`define __icarus_verilog
//`define __xilinx_verilog

labs/Lab1/paquin_lab/src/alu.v
`ifndef _include_alu_
`define _include_alu_

`timescale 1ns / 1ns

`include "compiler.v"

`ifdef __icarus_verilog
`define OP_NOP   4'b0000
`define OP_ADD   4'b0001
`define OP_SUB   4'b0010
`define OP_INC   4'b0011
`define OP_XOR   4'b0100
`define OP_CMP   4'b0101
`define OP_SADD  4'b0110
`define OP_SSUB  4'b0111
`define OP_SMULT 4'b1000
`define OP_SDIV  4'b1001
`define OP_A     4'b1010
`define OP_B     4'b1011
`else // __xilinx_verilog
`include "const.v"
`endif // __icarus_verilog

module Alu(
	input wire [15:0] a_data,
	input wire [15:0] b_data,

	input wire [ 3:0] alu_op,

	output reg [15:0] out,

	input wire clk,
	input wire rst
);
	
	wire signed [15:0] signed_a;
	wire signed [15:0] signed_b;

	assign signed_a = a_data;
	assign signed_b = b_data;
	
	always @(*) begin
		#1;
		case (alu_op)
			`OP_NOP:   out = 0;
			`OP_ADD:   out = a_data + b_data;
			`OP_SUB:   out = a_data - b_data;
			`OP_INC:   out = a_data + 1;
			`OP_XOR:   out = a_data ^ b_data;
			`OP_CMP:   out = a_data > b_data ? 16'b1 : 16'b0;
			`OP_SADD:  out = signed_a + signed_b;
			`OP_SSUB:  out = signed_a - signed_b;
			`OP_SMULT: out = signed_a * signed_b;
			`OP_SDIV:  out = signed_a / signed_b;
			`OP_A:     out = a_data;
			`OP_B:     out = b_data;
			default:   out = 16'b0;
		endcase
	end
endmodule

`endif // _include_alu_

labs/Lab1/paquin_lab/src/alu_tb.v
`timescale 1ns / 1ns

`include "compiler.v"

`ifdef __icarus_verilog
`include "alu.v"
`else // __xilinx_verilog
`include "const.v"
`endif // __icarus_verilog

module main();
	reg [15:0] a;
	reg [15:0] b;
	reg [3:0] op;

	wire [15:0] out;

	reg clk;
	reg rst;
	
	Alu uut(
		.a_data(a),
		.b_data(b),
		.alu_op(op),
		.out(out),
		.clk(clk),
		.rst(rst)
	);

	initial begin
		clk = 1;
		forever #5 clk = ~clk;
	end

	initial begin
		rst = 1;
		#10 rst = 0;
	end

	initial begin
		a <= 0;
		b <= 0;
		op <= 0;
	end

	initial begin
		$dumpfile("alu.vcd");
		$dumpvars(0, uut);
		$dumpvars(0, a, b, op, out, clk, rst);
		
		#10;
		a <= 7; b <= 5; op <= `OP_NOP;
		#10; op <= `OP_ADD;
		#10; op <= `OP_SUB;
		#10; op <= `OP_INC;
		#10; op <= `OP_XOR;
		#10; op <= `OP_CMP;
		#10; a <= 5; b <= 7;
		#10; op <= `OP_SADD;
		#10; op <= `OP_SSUB; a <= 7; b <= 5;
		#10; op <= `OP_SMULT;
		#10; op <= `OP_SDIV; a <= -75;
		#30; $finish;
	end

endmodule

labs/Lab1/paquin_lab/sim/alu.vcd
$date
	Mon Mar 12 18:25:40 2018
$end
$version
	Icarus Verilog
$end
$timescale
	1ns
$end
$scope module main $end
$scope module uut $end
$var wire 16 ! a_data [15:0] $end
$var wire 4 " alu_op [3:0] $end
$var wire 16 # b_data [15:0] $end
$var wire 1 $ clk $end
$var wire 1 % rst $end
$var wire 16 & signed_a [15:0] $end
$var wire 16 ' signed_b [15:0] $end
$var reg 16 ( out [15:0] $end
$upscope $end
$upscope $end
$scope module main $end
$var reg 16 ) a [15:0] $end
$upscope $end
$scope module main $end
$var reg 16 * b [15:0] $end
$upscope $end
$scope module main $end
$var reg 4 + op [3:0] $end
$upscope $end
$scope module main $end
$var wire 16 , out [15:0] $end
$upscope $end
$scope module main $end
$var reg 1 $ clk $end
$upscope $end
$scope module main $end
$var reg 1 % rst $end
$upscope $end
$enddefinitions $end
#0
$dumpvars
bx ,
b0 +
b0 *
b0 )
bx (
b0 '
b0 &
1%
1$
b0 #
b0 "
b0 !
$end
#1
b0 (
b0 ,
#5
0$
#10
b101 '
b101 #
b101 *
b111 &
b111 !
b111 )
1$
0%
#15
0$
#20
b1 "
b1 +
1$
#21
b1100 (
b1100 ,
#25
0$
#30
b10 "
b10 +
1$
#31
b10 (
b10 ,
#35
0$
#40
b11 "
b11 +
1$
#41
b1000 (
b1000 ,
#45
0$
#50
b100 "
b100 +
1$
#51
b10 (
b10 ,
#55
0$
#60
b101 "
b101 +
1$
#61
b1 (
b1 ,
#65
0$
#70
b111 '
b111 #
b111 *
b101 &
b101 !
b101 )
1$
#71
b0 (
b0 ,
#75
0$
#80
b110 "
b110 +
1$
#81
b1100 (
b1100 ,
#85
0$
#90
b101 '
b101 #
b101 *
b111 &
b111 !
b111 )
b111 "
b111 +
1$
#91
b10 (
b10 ,
#95
0$
#100
b1000 "
b1000 +
1$
#101
b100011 (
b100011 ,
#105
0$
#110
b1111111110110101 &
b1111111110110101 !
b1111111110110101 )
b1001 "
b1001 +
1$
#111
b1111111111110001 (
b1111111111110001 ,
