labs/Lab1/paquin_lab/src/const.v
`define SEL_NON 2'b00
`define SEL_REG 2'b01
`define SEL_MEM 2'b10
`define SEL_IMM 2'b11

`define PCSEL_INC 3'b000
`define PCSEL_JMP 3'b001
`define PCSEL_JE  3'b010
`define PCSEL_JNE 3'b011
`define PCSEL_HLT 3'b100

`define INST_HALT 4'b0000
`define INST_INC  4'b0001
`define INST_JMP  4'b0010
`define INST_JNE  4'b0011
`define INST_JE   4'b0100
`define INST_ADD  4'b0101
`define INST_SUB  4'b0110
`define INST_XOR  4'b0111
`define INST_CMP  4'b1000
`define INST_LIMM 4'b1001
`define INST_MOV  4'b1010
`define INST_SW   4'b1011
`define INST_LW   4'b1100
`define INST_SPEC 4'b1101

`define OP_NOP   4'b0000
`define OP_ADD   4'b0001
`define OP_SUB   4'b0010
`define OP_INC   4'b0011
`define OP_XOR   4'b0100
`define OP_CMP   4'b0101
`define OP_SADD  4'b0110
`define OP_SSUB  4'b0111
`define OP_SMULT 4'b1000
`define OP_SDIV  4'b1001
`define OP_A     4'b1010
`define OP_B     4'b1011

`define CHAR_SPACE 0
`define CHAR_A 1
`define CHAR_B 2
`define CHAR_C 3
`define CHAR_D 4
`define CHAR_E 5
`define CHAR_F 6
`define CHAR_G 7
`define CHAR_H 8
`define CHAR_I 9
`define CHAR_J 10
`define CHAR_K 11
`define CHAR_L 12
`define CHAR_M 13
`define CHAR_N 14
`define CHAR_O 15
`define CHAR_P 16
`define CHAR_Q 17
`define CHAR_R 18
`define CHAR_S 19
`define CHAR_T 20
`define CHAR_U 21
`define CHAR_V 22
`define CHAR_W 23
`define CHAR_X 24
`define CHAR_Y 25
`define CHAR_Z 26
`define CHAR_0 27
`define CHAR_1 28
`define CHAR_2 29
`define CHAR_3 30
`define CHAR_4 31
`define CHAR_5 32
`define CHAR_6 33
`define CHAR_7 34
`define CHAR_8 35
`define CHAR_9 36

`define SEG7_0 7'b0000001
`define SEG7_1 7'b1001111
`define SEG7_2 7'b0010010
`define SEG7_3 7'b0000110
`define SEG7_4 7'b1001100
`define SEG7_5 7'b0100100
`define SEG7_6 7'b0100000
`define SEG7_7 7'b0001111
`define SEG7_8 7'b0000000
`define SEG7_9 7'b0000100

labs/Lab1/paquin_lab/src/compiler.v
`define __icarus_verilog
//`define __xilinx_verilog

labs/Lab1/paquin_lab/src/memory.v
`ifndef _include_memory_
`define _include_memory_

`timescale 1ns / 1ns

`include "compiler.v"

`ifdef __icarus_verilog
`else // __xilinx_verilog
`include "const.v"
`endif // __icarus_verilog

module Memory(
	input  wire [11:0] r_addr,
	output reg  [15:0] r_data,

	input  wire [11:0] w_addr,
	input  wire [15:0] w_data,
	input  wire        w_en,

	input  wire [11:0] pc,
	output reg  [15:0] inst,

	input  wire        clk, 
	input  wire        rst
);
	reg [15:0] memory[4095:0];

	integer ii;
	initial begin
		`ifdef __icarus_verilog
		for (ii=0; ii<4096; ii=ii+1) begin
			memory[ii] = 0;
		end
		`endif // __icarus_verilog

		$readmemb("memory.list", memory);
	end
	
	always @(negedge clk) begin
		r_data <= memory[r_addr];
	end
	
	always @(posedge clk) begin
		if (rst) begin
			inst <= 16'b1010_000000_000000; // mov r0 r0 (noop)
		end else begin
			inst <= memory[pc];
		end
	end

	always @(posedge clk) begin
		if (rst) begin
		end else if (w_en) begin
			$display("%t sw [%d] %d", $time, w_addr, w_data);
			memory[w_addr] <= w_data;
		end
	end

endmodule

`endif // _include_memory_

labs/Lab1/paquin_lab/src/memory_tb.v
`timescale 1ns / 1ns

`include "compiler.v"

`ifdef __icarus_verilog
`include "memory.v"
`else // __xilinx_verilog
`include "const.v"
`endif // __icarus_verilog

module main();
	reg  [11:0] r_addr;
	wire [15:0] r_data;
	
	reg  [11:0] w_addr;
	reg  [15:0] w_data;
	reg         w_en;

	reg  [11:0] pc;
	wire [15:0] inst;

	reg clk;
	reg rst;

	Memory uut(
		.r_addr(r_addr),
		.r_data(r_data),
		.w_addr(w_addr),
		.w_data(w_data),
		.w_en(w_en),
		.pc(pc),
		.inst(inst),
		.clk(clk),
		.rst(rst)
	);

	initial begin
		rst = 1;
		#10 rst = 0;
	end

	initial begin
		clk = 1;
		forever #5 clk = ~clk;
	end

	initial begin
		r_addr <= 0;
		w_addr <= 0;
		w_data <= 0;
		w_en <= 0;
		pc <= 31;
	end

	initial begin
		#55;
		forever #10 pc = pc + 1;
	end

	initial begin
		$dumpfile("memory.vcd");
		$dumpvars(0, uut);
		$dumpvars(0, r_addr, r_data, w_addr, w_data, w_en, pc, inst, clk, rst);
		$dumpvars(0, uut.memory[31]);

		//#10; w_data <= 16'h31aa; w_addr <= 31; w_en <= 1;
		//#10; w_data <= 16'h32bb; w_addr <= 32;
		//#10; w_data <= 16'h33cc; w_addr <= 33;
		//#10; w_data <= 16'h34dd; w_addr <= 34;
		//#10; w_data <= 16'h35ee; w_addr <= 35;
		//#10; w_data <= 16'h36ff; w_addr <= 36;
		#10; pc <= 31;
		#10; r_addr <= 36; w_en <= 0;
		#10; r_addr <= 35;
		#10; r_addr <= 34; //#1 pc <= 31;
		#10; r_addr <= 33;
		#10; r_addr <= 32;
		#10; r_addr <= 31;
		#10; r_addr <= 30;
		#400 $finish;
	end
endmodule

labs/Lab1/paquin_lab/sim/memory.vcd
$date
	Mon Mar 12 18:25:50 2018
$end
$version
	Icarus Verilog
$end
$timescale
	1ns
$end
$scope module main $end
$scope module uut $end
$var wire 1 ! clk $end
$var wire 12 " pc [11:0] $end
$var wire 12 # r_addr [11:0] $end
$var wire 1 $ rst $end
$var wire 12 % w_addr [11:0] $end
$var wire 16 & w_data [15:0] $end
$var wire 1 ' w_en $end
$var reg 16 ( inst [15:0] $end
$var reg 16 ) r_data [15:0] $end
$var integer 32 * ii [31:0] $end
$upscope $end
$upscope $end
$scope module main $end
$var reg 12 + r_addr [11:0] $end
$upscope $end
$scope module main $end
$var wire 16 , r_data [15:0] $end
$upscope $end
$scope module main $end
$var reg 12 - w_addr [11:0] $end
$upscope $end
$scope module main $end
$var reg 16 . w_data [15:0] $end
$upscope $end
$scope module main $end
$var reg 1 ' w_en $end
$upscope $end
$scope module main $end
$var reg 12 / pc [11:0] $end
$upscope $end
$scope module main $end
$var wire 16 0 inst [15:0] $end
$upscope $end
$scope module main $end
$var reg 1 ! clk $end
$upscope $end
$scope module main $end
$var reg 1 $ rst $end
$upscope $end
$scope module main $end
$scope module uut $end
$var reg 16 1 \memory[31] [15:0] $end
$upscope $end
$upscope $end
$enddefinitions $end
#0
$dumpvars
b1001000000001010 1
b1010000000000000 0
b11111 /
b0 .
b0 -
bx ,
b0 +
b1000000000000 *
bx )
b1010000000000000 (
0'
b0 &
b0 %
1$
b0 #
b11111 "
1!
$end
#5
b0 )
b0 ,
0!
#10
b1001000000001010 (
b1001000000001010 0
1!
0$
#15
0!
#20
b100100 #
b100100 +
1!
#25
b1000000000001 )
b1000000000001 ,
0!
#30
b100011 #
b100011 +
1!
#35
b1010000000000001 )
b1010000000000001 ,
0!
#40
b100010 #
b100010 +
1!
#45
b1011000000000001 )
b1011000000000001 ,
0!
#50
b100001 #
b100001 +
1!
#55
b1001000010010100 )
b1001000010010100 ,
0!
#60
b100000 #
b100000 +
1!
#65
b1001000001001011 )
b1001000001001011 ,
0!
b100000 "
b100000 /
#70
b1001000001001011 (
b1001000001001011 0
b11111 #
b11111 +
1!
#75
b1001000000001010 )
b1001000000001010 ,
0!
b100001 "
b100001 /
#80
b1001000010010100 (
b1001000010010100 0
b11110 #
b11110 +
1!
#85
b0 )
b0 ,
0!
b100010 "
b100010 /
#90
b1011000000000001 (
b1011000000000001 0
1!
#95
0!
b100011 "
b100011 /
#100
b1010000000000001 (
b1010000000000001 0
1!
#105
0!
b100100 "
b100100 /
#110
b1000000000001 (
b1000000000001 0
1!
#115
0!
b100101 "
b100101 /
#120
b1000000000000010 (
b1000000000000010 0
1!
#125
0!
b100110 "
b100110 /
#130
b11000000100010 (
b11000000100010 0
1!
#135
0!
b100111 "
b100111 /
#140
b1001000000010011 (
b1001000000010011 0
1!
#145
0!
b101000 "
b101000 /
#150
b1100000011000000 (
b1100000011000000 0
1!
#155
0!
b101001 "
b101001 /
#160
b1000000000011 (
b1000000000011 0
1!
#165
0!
b101010 "
b101010 /
#170
b1011000000000011 (
b1011000000000011 0
1!
#175
0!
b101011 "
b101011 /
#180
b1100000011000000 (
b1100000011000000 0
1!
#185
0!
b101100 "
b101100 /
#190
b1000000000011 (
b1000000000011 0
1!
#195
0!
b101101 "
b101101 /
#200
b1011000000000011 (
b1011000000000011 0
1!
#205
0!
b101110 "
b101110 /
#210
b1001000000111100 (
b1001000000111100 0
1!
#215
0!
b101111 "
b101111 /
#220
b1001000001101000 (
b1001000001101000 0
1!
#225
0!
b110000 "
b110000 /
#230
b101000000000001 (
b101000000000001 0
1!
#235
0!
b110001 "
b110001 /
#240
b1001000010011110 (
b1001000010011110 0
1!
#245
0!
b110010 "
b110010 /
#250
b110000001000010 (
b110000001000010 0
1!
#255
0!
b110011 "
b110011 /
#260
b1011000000000001 (
b1011000000000001 0
1!
#265
0!
b110100 "
b110100 /
#270
b1000000000000 (
b1000000000000 0
1!
#275
0!
b110101 "
b110101 /
#280
b1001000010000101 (
b1001000010000101 0
1!
#285
0!
b110110 "
b110110 /
#290
b1001000001001101 (
b1001000001001101 0
1!
#295
0!
b110111 "
b110111 /
#300
b111000001000010 (
b111000001000010 0
1!
#305
0!
b111000 "
b111000 /
#310
b1011000000000001 (
b1011000000000001 0
1!
#315
0!
b111001 "
b111001 /
#320
b1000000000000 (
b1000000000000 0
1!
#325
0!
b111010 "
b111010 /
#330
b0 (
b0 0
1!
#335
0!
b111011 "
b111011 /
#340
1!
#345
0!
b111100 "
b111100 /
#350
1!
#355
0!
b111101 "
b111101 /
#360
1!
#365
0!
b111110 "
b111110 /
#370
1!
#375
0!
b111111 "
b111111 /
#380
1!
#385
0!
b1000000 "
b1000000 /
#390
1!
#395
0!
b1000001 "
b1000001 /
#400
1!
#405
0!
b1000010 "
b1000010 /
#410
1!
#415
0!
b1000011 "
b1000011 /
#420
1!
#425
0!
b1000100 "
b1000100 /
#430
1!
#435
0!
b1000101 "
b1000101 /
#440
1!
#445
0!
b1000110 "
b1000110 /
#450
1!
#455
0!
b1000111 "
b1000111 /
#460
1!
#465
0!
b1001000 "
b1001000 /
#470
1!
#475
0!
b1001001 "
b1001001 /
