labs/Lab1/paquin_lab/src/const.v
`define SEL_NON 2'b00
`define SEL_REG 2'b01
`define SEL_MEM 2'b10
`define SEL_IMM 2'b11

`define PCSEL_INC 3'b000
`define PCSEL_JMP 3'b001
`define PCSEL_JE  3'b010
`define PCSEL_JNE 3'b011
`define PCSEL_HLT 3'b100

`define INST_HALT 4'b0000
`define INST_INC  4'b0001
`define INST_JMP  4'b0010
`define INST_JNE  4'b0011
`define INST_JE   4'b0100
`define INST_ADD  4'b0101
`define INST_SUB  4'b0110
`define INST_XOR  4'b0111
`define INST_CMP  4'b1000
`define INST_LIMM 4'b1001
`define INST_MOV  4'b1010
`define INST_SW   4'b1011
`define INST_LW   4'b1100
`define INST_SPEC 4'b1101

`define OP_NOP   4'b0000
`define OP_ADD   4'b0001
`define OP_SUB   4'b0010
`define OP_INC   4'b0011
`define OP_XOR   4'b0100
`define OP_CMP   4'b0101
`define OP_SADD  4'b0110
`define OP_SSUB  4'b0111
`define OP_SMULT 4'b1000
`define OP_SDIV  4'b1001
`define OP_A     4'b1010
`define OP_B     4'b1011

`define CHAR_SPACE 0
`define CHAR_A 1
`define CHAR_B 2
`define CHAR_C 3
`define CHAR_D 4
`define CHAR_E 5
`define CHAR_F 6
`define CHAR_G 7
`define CHAR_H 8
`define CHAR_I 9
`define CHAR_J 10
`define CHAR_K 11
`define CHAR_L 12
`define CHAR_M 13
`define CHAR_N 14
`define CHAR_O 15
`define CHAR_P 16
`define CHAR_Q 17
`define CHAR_R 18
`define CHAR_S 19
`define CHAR_T 20
`define CHAR_U 21
`define CHAR_V 22
`define CHAR_W 23
`define CHAR_X 24
`define CHAR_Y 25
`define CHAR_Z 26
`define CHAR_0 27
`define CHAR_1 28
`define CHAR_2 29
`define CHAR_3 30
`define CHAR_4 31
`define CHAR_5 32
`define CHAR_6 33
`define CHAR_7 34
`define CHAR_8 35
`define CHAR_9 36

`define SEG7_0 7'b0000001
`define SEG7_1 7'b1001111
`define SEG7_2 7'b0010010
`define SEG7_3 7'b0000110
`define SEG7_4 7'b1001100
`define SEG7_5 7'b0100100
`define SEG7_6 7'b0100000
`define SEG7_7 7'b0001111
`define SEG7_8 7'b0000000
`define SEG7_9 7'b0000100

labs/Lab1/paquin_lab/src/compiler.v
`define __icarus_verilog
//`define __xilinx_verilog

labs/Lab1/paquin_lab/src/regfile.v
`ifndef _include_regfile_
`define _include_regfile_

`timescale 1ns / 1ns

`include "compiler.v"

`ifdef __icarus_verilog
`else // __xilinx_verilog
`include "const.v"
`endif // __icarus_verilog

module Regfile(
	output reg  [ 15:0] a_data,
	input  wire [  2:0] a_sel,

	output reg  [ 15:0] b_data,
	input  wire [  2:0] b_sel,

	input  wire [ 15:0] w_data,
	input  wire [  2:0] w_sel,
	input  wire 	    w_en,

	input  wire [ 15:0] r6,
	
	output wire [111:0] regexpose,

	input clk,
	input rst
);

	reg [15:0] registers[5:0];

	assign regexpose = {registers[0], registers[1], registers[2], registers[3], registers[4], registers[5], r6};
	
	always @(*) begin
		#1;
		if (a_sel <= 5) begin
			a_data = registers[a_sel];
		end else if (a_sel == 6) begin
			a_data = r6;
		end else begin
			a_data = 0;
		end

		if (b_sel <= 5) begin
			b_data = registers[b_sel];
		end else if (b_sel == 6) begin
			b_data = r6;
		end else begin
			b_data = 0;
		end
	end


	integer ii;

	always @(posedge clk) begin
		if (rst) begin
			for (ii=0; ii<6; ii=ii+1) begin
				registers[ii] <= 0;
			end
		end else if (w_en) begin
			if (w_sel <= 5) begin
				registers[w_sel] <= w_data;
			end 
		end
	end

endmodule

`endif // _include_regfile_

labs/Lab1/paquin_lab/src/regfile_tb.v
`timescale 1ns / 1ns

`include "compiler.v"

`ifdef __icarus_verilog
`include "regfile.v"
`else // __xilinx_verilog
`include "const.v"
`endif // __icarus_verilog

module main();
	wire [15:0] a_data, b_data;
	reg  [ 2:0] a_sel,  b_sel;

	reg  [15:0] w_data;
	reg  [ 2:0] w_sel;
	reg         w_en;

	reg clk, rst;

	Regfile uut(
		.a_data(a_data),
		.a_sel (a_sel),
		
		.b_data(b_data),
		.b_sel(b_sel),

		.w_data(w_data),
		.w_sel (w_sel),
		.w_en  (w_en),

		.clk(clk),
		.rst(rst)
	);

	initial begin
		rst = 1;
		#10 rst = 0;
		#990 $finish;
	end

	initial begin
		clk = 1;
		forever #5 clk = ~clk;
	end

	initial begin
		a_sel  <= 0;
		b_sel  <= 0;
		w_sel  <= 0;
		w_data <= 0;
		w_en   <= 0;
	end

	initial begin
		$dumpfile("regfile.vcd");
		$dumpvars(0, uut);
		$dumpvars(0, w_data, w_en, w_sel, a_data, a_sel, b_data, b_sel, clk, rst);
		$dumpvars(0, uut.registers[0], uut.registers[1], uut.registers[2], uut.registers[3], uut.registers[4], uut.registers[5]);

		#10;
		w_data <= 16'hf000; w_en <= 1; w_sel <= 1;
		a_sel <= 1;
		#10; 
		w_data <= 16'hfbbb; w_en <= 0; w_sel <= 1;
		b_sel <= 3;
		#10; 
		w_data <= 16'h5678; w_en <= 1; w_sel <= 5;
		#10; 
		w_data <= 16'h4567; w_en <= 1; w_sel <= 4;
		#10; 
		w_data <= 16'h3456; w_en <= 1; w_sel <= 3;
		#10; 
		w_data <= 16'h2345; w_en <= 1; w_sel <= 2;
		#10; 
		w_data <= 16'h1234; w_en <= 1; w_sel <= 1;
		#10; 
		w_data <= 16'h0123; w_en <= 1; w_sel <= 0;
		#10; 
		w_en <= 0;
		a_sel <= 0;
		b_sel <= 1;
		#10;
		a_sel <= 2;
		b_sel <= 3;
		#10;
		a_sel <= 4;
		b_sel <= 5;
		#10;
		a_sel <= 6;
		b_sel <= 7;
	end
endmodule

labs/Lab1/paquin_lab/sim/regfile.vcd
$date
	Mon Mar 12 18:26:27 2018
$end
$version
	Icarus Verilog
$end
$timescale
	1ns
$end
$scope module main $end
$scope module uut $end
$var wire 3 ! a_sel [2:0] $end
$var wire 3 " b_sel [2:0] $end
$var wire 1 # clk $end
$var wire 16 $ r6 [15:0] $end
$var wire 1 % rst $end
$var wire 16 & w_data [15:0] $end
$var wire 1 ' w_en $end
$var wire 3 ( w_sel [2:0] $end
$var wire 112 ) regexpose [111:0] $end
$var reg 16 * a_data [15:0] $end
$var reg 16 + b_data [15:0] $end
$var integer 32 , ii [31:0] $end
$upscope $end
$upscope $end
$scope module main $end
$var reg 16 - w_data [15:0] $end
$upscope $end
$scope module main $end
$var reg 1 ' w_en $end
$upscope $end
$scope module main $end
$var reg 3 . w_sel [2:0] $end
$upscope $end
$scope module main $end
$var wire 16 / a_data [15:0] $end
$upscope $end
$scope module main $end
$var reg 3 0 a_sel [2:0] $end
$upscope $end
$scope module main $end
$var wire 16 1 b_data [15:0] $end
$upscope $end
$scope module main $end
$var reg 3 2 b_sel [2:0] $end
$upscope $end
$scope module main $end
$var reg 1 # clk $end
$upscope $end
$scope module main $end
$var reg 1 % rst $end
$upscope $end
$scope module main $end
$scope module uut $end
$var reg 16 3 \registers[0] [15:0] $end
$upscope $end
$upscope $end
$scope module main $end
$scope module uut $end
$var reg 16 4 \registers[1] [15:0] $end
$upscope $end
$upscope $end
$scope module main $end
$scope module uut $end
$var reg 16 5 \registers[2] [15:0] $end
$upscope $end
$upscope $end
$scope module main $end
$scope module uut $end
$var reg 16 6 \registers[3] [15:0] $end
$upscope $end
$upscope $end
$scope module main $end
$scope module uut $end
$var reg 16 7 \registers[4] [15:0] $end
$upscope $end
$upscope $end
$scope module main $end
$scope module uut $end
$var reg 16 8 \registers[5] [15:0] $end
$upscope $end
$upscope $end
$enddefinitions $end
#0
$dumpvars
b0 8
b0 7
b0 6
b0 5
b0 4
b0 3
b0 2
bx 1
b0 0
bx /
b0 .
b0 -
b110 ,
bx +
bx *
b0zzzzzzzzzzzzzzzz )
b0 (
0'
b0 &
1%
bz $
1#
b0 "
b0 !
$end
#1
b0 +
b0 1
b0 *
b0 /
#5
0#
#10
b1 !
b1 0
b1 (
b1 .
1'
b1111000000000000 &
b1111000000000000 -
1#
0%
#15
0#
#20
b1111000000000000 4
b11110000000000000000000000000000000000000000000000000000000000000000000000000000zzzzzzzzzzzzzzzz )
b11 "
b11 2
0'
b1111101110111011 &
b1111101110111011 -
1#
#21
b1111000000000000 *
b1111000000000000 /
#25
0#
#30
b101 (
b101 .
1'
b101011001111000 &
b101011001111000 -
1#
#35
0#
#40
b101011001111000 8
b11110000000000000000000000000000000000000000000000000000000000000101011001111000zzzzzzzzzzzzzzzz )
b100 (
b100 .
b100010101100111 &
b100010101100111 -
1#
#45
0#
#50
b100010101100111 7
b11110000000000000000000000000000000000000000000001000101011001110101011001111000zzzzzzzzzzzzzzzz )
b11 (
b11 .
b11010001010110 &
b11010001010110 -
1#
#55
0#
#60
b11010001010110 6
b11110000000000000000000000000000001101000101011001000101011001110101011001111000zzzzzzzzzzzzzzzz )
b10 (
b10 .
b10001101000101 &
b10001101000101 -
1#
#61
b11010001010110 +
b11010001010110 1
#65
0#
#70
b10001101000101 5
b11110000000000000010001101000101001101000101011001000101011001110101011001111000zzzzzzzzzzzzzzzz )
b1 (
b1 .
b1001000110100 &
b1001000110100 -
1#
#75
0#
#80
b1001000110100 4
b10010001101000010001101000101001101000101011001000101011001110101011001111000zzzzzzzzzzzzzzzz )
b0 (
b0 .
b100100011 &
b100100011 -
1#
#81
b1001000110100 *
b1001000110100 /
#85
0#
#90
b100100011 3
b10010001100010010001101000010001101000101001101000101011001000101011001110101011001111000zzzzzzzzzzzzzzzz )
b1 "
b1 2
b0 !
b0 0
0'
1#
#91
b1001000110100 +
b1001000110100 1
b100100011 *
b100100011 /
#95
0#
#100
b11 "
b11 2
b10 !
b10 0
1#
#101
b11010001010110 +
b11010001010110 1
b10001101000101 *
b10001101000101 /
#105
0#
#110
b101 "
b101 2
b100 !
b100 0
1#
#111
b101011001111000 +
b101011001111000 1
b100010101100111 *
b100010101100111 /
#115
0#
#120
b111 "
b111 2
b110 !
b110 0
1#
#121
b0 +
b0 1
bz *
bz /
